{
  "basicConfig": {
    "author": "熊猫哥",
    "apiFileName": "brand",
    "apiFileNameFirstCase": "Brand",
    "routerParentDir": "template-demo",
    "addEditPath": "CRUDForm",
    "detailPath": "CRUDDetail",
    "dataTime": "2022-10-01 16:07:56"
  },
  "apiConfig": {
    "queryApi": "/integration-front/brand/selectPage",
    "queryMethod": "get",
    "deleteApi": "/integration-front/brand/deleteById",
    "deleteMethod": "delete",
    "multiDeleteApi": "/integration-front/brand/deleteBatchIds",
    "multiDeleteMethod": "delete"
  },
  "tableConfig": {
    "isAdd": "true",
    "isDelete": "true",
    "isMulDelete": "true",
    "isEdit": "true",
    "isPagination": "true",
    "isDetail": "true",
    "isTableMulChoose": "true",
    "isExport": "false"
  },
  "queryConfig": [
    {
      "columnName": "name",
      "desc": "品牌名字",
      "uuid": "093ada70-8c8e-4ee4-a6eb-a837207911c7",
      "field": "name",
      "fieldCase": "Name",
      "originField": "name",
      "componentType": "input",
      "rule": "isNotNull",
      "children": "children",
      "width": "100",
      "api": "",
      "method": "get",
      "labelKey": "name",
      "valueKey": "code",
      "controlType": "elInput"
    },
    {
      "columnName": "startEndArr",
      "desc": "查询时间范围",
      "uuid": "c14dd34f-5c55-48fd-bd8a-cb1ec3dc6898",
      "field": "startEndArr",
      "fieldCase": "Startendarr",
      "originField": "startEndArr",
      "componentType": "daterange",
      "rule": "isNotNull",
      "children": "children",
      "width": 150,
      "api": "",
      "method": "get",
      "labelKey": "name",
      "valueKey": "code",
      "controlType": "elInput"
    }
  ],
  "tableList": [
    {
      "columnName": "name",
      "desc": "品牌名字",
      "uuid": "2513f205-4e68-49eb-83d1-eb7a3a4c1754",
      "field": "name",
      "fieldCase": "Name",
      "originField": "name",
      "componentType": "input",
      "rule": "isNotNull",
      "children": "children",
      "width": 100,
      "api": "",
      "method": "get",
      "labelKey": "name",
      "valueKey": "code",
      "isTemplate": "false",
      "controlType": "elInput"
    },
    {
      "columnName": "image",
      "desc": "图片地址",
      "uuid": "ee801eb1-81dc-475e-b1b3-ad3522218b91",
      "field": "image",
      "fieldCase": "Image",
      "originField": "image",
      "componentType": "image",
      "rule": "isNotNull",
      "children": "children",
      "width": 100,
      "api": "",
      "method": "get",
      "labelKey": "name",
      "valueKey": "code",
      "isTemplate": "true",
      "controlType": "elInput"
    },
    {
      "columnName": "letter",
      "desc": "首字母",
      "uuid": "3223c62b-c28f-4419-94ba-275afca97100",
      "field": "letter",
      "fieldCase": "Letter",
      "originField": "letter",
      "componentType": "input",
      "rule": "isNotNull",
      "children": "children",
      "width": 100,
      "api": "",
      "method": "get",
      "labelKey": "name",
      "valueKey": "code",
      "isTemplate": "false",
      "controlType": "elInput"
    },
    {
      "columnName": "seq",
      "desc": "排序",
      "uuid": "501e9286-4cc6-41b0-9abe-28ae9412528f",
      "field": "seq",
      "fieldCase": "Seq",
      "originField": "seq",
      "componentType": "input",
      "rule": "isNotNull",
      "children": "children",
      "width": 100,
      "api": "",
      "method": "get",
      "labelKey": "name",
      "valueKey": "code",
      "isTemplate": "false",
      "controlType": "elInput"
    },
    {
      "columnName": "createTime",
      "desc": "创建时间",
      "uuid": "4e311ffc-13c8-4217-89d6-29a2693e7fa7",
      "field": "createTime",
      "fieldCase": "Createtime",
      "originField": "createTime",
      "componentType": "daterange",
      "rule": "isNotNull",
      "children": "children",
      "width": 100,
      "api": "",
      "method": "get",
      "labelKey": "name",
      "valueKey": "code",
      "isTemplate": "false",
      "controlType": "elInput"
    },
    {
      "columnName": "updateTime",
      "desc": "更新时间",
      "uuid": "2d84d57c-a181-4cdd-a824-c560987d2c7e",
      "field": "updateTime",
      "fieldCase": "Updatetime",
      "originField": "updateTime",
      "componentType": "daterange",
      "rule": "isNotNull",
      "children": "children",
      "width": 100,
      "api": "",
      "method": "get",
      "labelKey": "name",
      "valueKey": "code",
      "isTemplate": "false",
      "controlType": "elInput"
    }
  ]
}